{
  "formatVersion": 1,
  "database": {
    "version": 29,
    "identityHash": "a11a38e1433a563cd60a2a153e91acfd",
    "entities": [
      {
        "tableName": "currencies",
        "createSql": "CREATE TABLE IF NOT EXISTS `${TABLE_NAME}` (`code` TEXT NOT NULL, `symbol` TEXT NOT NULL, `defaultName` TEXT NOT NULL, `decimalDigits` INTEGER NOT NULL, PRIMARY KEY(`code`))",
        "fields": [
          {
            "fieldPath": "code",
            "columnName": "code",
            "affinity": "TEXT",
            "notNull": true
          },
          {
            "fieldPath": "symbol",
            "columnName": "symbol",
            "affinity": "TEXT",
            "notNull": true
          },
          {
            "fieldPath": "defaultName",
            "columnName": "defaultName",
            "affinity": "TEXT",
            "notNull": true
          },
          {
            "fieldPath": "decimalDigits",
            "columnName": "decimalDigits",
            "affinity": "INTEGER",
            "notNull": true
          }
        ],
        "primaryKey": {
          "autoGenerate": false,
          "columnNames": [
            "code"
          ]
        }
      },
      {
        "tableName": "exchange_rates",
        "createSql": "CREATE TABLE IF NOT EXISTS `${TABLE_NAME}` (`baseCurrencyCode` TEXT NOT NULL, `currencyCode` TEXT NOT NULL, `rate` TEXT NOT NULL, `lastUpdated` INTEGER NOT NULL, PRIMARY KEY(`baseCurrencyCode`, `currencyCode`))",
        "fields": [
          {
            "fieldPath": "baseCurrencyCode",
            "columnName": "baseCurrencyCode",
            "affinity": "TEXT",
            "notNull": true
          },
          {
            "fieldPath": "currencyCode",
            "columnName": "currencyCode",
            "affinity": "TEXT",
            "notNull": true
          },
          {
            "fieldPath": "rate",
            "columnName": "rate",
            "affinity": "TEXT",
            "notNull": true
          },
          {
            "fieldPath": "lastUpdated",
            "columnName": "lastUpdated",
            "affinity": "INTEGER",
            "notNull": true
          }
        ],
        "primaryKey": {
          "autoGenerate": false,
          "columnNames": [
            "baseCurrencyCode",
            "currencyCode"
          ]
        }
      },
      {
        "tableName": "groups",
        "createSql": "CREATE TABLE IF NOT EXISTS `${TABLE_NAME}` (`id` TEXT NOT NULL, `name` TEXT NOT NULL, `description` TEXT, `currencyCode` TEXT NOT NULL, `extraCurrencies` TEXT NOT NULL, `memberIds` TEXT NOT NULL, `mainImagePath` TEXT, `createdAtMillis` INTEGER, `lastUpdatedAtMillis` INTEGER, `syncStatus` TEXT NOT NULL, PRIMARY KEY(`id`))",
        "fields": [
          {
            "fieldPath": "id",
            "columnName": "id",
            "affinity": "TEXT",
            "notNull": true
          },
          {
            "fieldPath": "name",
            "columnName": "name",
            "affinity": "TEXT",
            "notNull": true
          },
          {
            "fieldPath": "description",
            "columnName": "description",
            "affinity": "TEXT"
          },
          {
            "fieldPath": "currencyCode",
            "columnName": "currencyCode",
            "affinity": "TEXT",
            "notNull": true
          },
          {
            "fieldPath": "extraCurrencies",
            "columnName": "extraCurrencies",
            "affinity": "TEXT",
            "notNull": true
          },
          {
            "fieldPath": "memberIds",
            "columnName": "memberIds",
            "affinity": "TEXT",
            "notNull": true
          },
          {
            "fieldPath": "mainImagePath",
            "columnName": "mainImagePath",
            "affinity": "TEXT"
          },
          {
            "fieldPath": "createdAtMillis",
            "columnName": "createdAtMillis",
            "affinity": "INTEGER"
          },
          {
            "fieldPath": "lastUpdatedAtMillis",
            "columnName": "lastUpdatedAtMillis",
            "affinity": "INTEGER"
          },
          {
            "fieldPath": "syncStatus",
            "columnName": "syncStatus",
            "affinity": "TEXT",
            "notNull": true
          }
        ],
        "primaryKey": {
          "autoGenerate": false,
          "columnNames": [
            "id"
          ]
        }
      },
      {
        "tableName": "expenses",
        "createSql": "CREATE TABLE IF NOT EXISTS `${TABLE_NAME}` (`id` TEXT NOT NULL, `groupId` TEXT NOT NULL, `title` TEXT NOT NULL, `sourceAmount` INTEGER NOT NULL, `sourceCurrency` TEXT NOT NULL, `groupAmount` INTEGER NOT NULL, `groupCurrency` TEXT NOT NULL, `exchangeRate` TEXT NOT NULL, `category` TEXT, `vendor` TEXT, `notes` TEXT, `paymentMethod` TEXT NOT NULL, `paymentStatus` TEXT, `dueDateMillis` INTEGER, `receiptLocalUri` TEXT, `receiptMimeType` TEXT, `receiptCapturedAtMillis` INTEGER, `receiptRemoteUrl` TEXT, `createdBy` TEXT NOT NULL, `payerType` TEXT NOT NULL, `payerId` TEXT, `splitType` TEXT NOT NULL, `createdAtMillis` INTEGER, `lastUpdatedAtMillis` INTEGER, `cashTranchesJson` TEXT, `addOnsJson` TEXT, `syncStatus` TEXT NOT NULL, PRIMARY KEY(`id`), FOREIGN KEY(`groupId`) REFERENCES `groups`(`id`) ON UPDATE NO ACTION ON DELETE CASCADE )",
        "fields": [
          {
            "fieldPath": "id",
            "columnName": "id",
            "affinity": "TEXT",
            "notNull": true
          },
          {
            "fieldPath": "groupId",
            "columnName": "groupId",
            "affinity": "TEXT",
            "notNull": true
          },
          {
            "fieldPath": "title",
            "columnName": "title",
            "affinity": "TEXT",
            "notNull": true
          },
          {
            "fieldPath": "sourceAmount",
            "columnName": "sourceAmount",
            "affinity": "INTEGER",
            "notNull": true
          },
          {
            "fieldPath": "sourceCurrency",
            "columnName": "sourceCurrency",
            "affinity": "TEXT",
            "notNull": true
          },
          {
            "fieldPath": "groupAmount",
            "columnName": "groupAmount",
            "affinity": "INTEGER",
            "notNull": true
          },
          {
            "fieldPath": "groupCurrency",
            "columnName": "groupCurrency",
            "affinity": "TEXT",
            "notNull": true
          },
          {
            "fieldPath": "exchangeRate",
            "columnName": "exchangeRate",
            "affinity": "TEXT",
            "notNull": true
          },
          {
            "fieldPath": "category",
            "columnName": "category",
            "affinity": "TEXT"
          },
          {
            "fieldPath": "vendor",
            "columnName": "vendor",
            "affinity": "TEXT"
          },
          {
            "fieldPath": "notes",
            "columnName": "notes",
            "affinity": "TEXT"
          },
          {
            "fieldPath": "paymentMethod",
            "columnName": "paymentMethod",
            "affinity": "TEXT",
            "notNull": true
          },
          {
            "fieldPath": "paymentStatus",
            "columnName": "paymentStatus",
            "affinity": "TEXT"
          },
          {
            "fieldPath": "dueDateMillis",
            "columnName": "dueDateMillis",
            "affinity": "INTEGER"
          },
          {
            "fieldPath": "receiptLocalUri",
            "columnName": "receiptLocalUri",
            "affinity": "TEXT"
          },
          {
            "fieldPath": "receiptMimeType",
            "columnName": "receiptMimeType",
            "affinity": "TEXT"
          },
          {
            "fieldPath": "receiptCapturedAtMillis",
            "columnName": "receiptCapturedAtMillis",
            "affinity": "INTEGER"
          },
          {
            "fieldPath": "receiptRemoteUrl",
            "columnName": "receiptRemoteUrl",
            "affinity": "TEXT"
          },
          {
            "fieldPath": "createdBy",
            "columnName": "createdBy",
            "affinity": "TEXT",
            "notNull": true
          },
          {
            "fieldPath": "payerType",
            "columnName": "payerType",
            "affinity": "TEXT",
            "notNull": true
          },
          {
            "fieldPath": "payerId",
            "columnName": "payerId",
            "affinity": "TEXT"
          },
          {
            "fieldPath": "splitType",
            "columnName": "splitType",
            "affinity": "TEXT",
            "notNull": true
          },
          {
            "fieldPath": "createdAtMillis",
            "columnName": "createdAtMillis",
            "affinity": "INTEGER"
          },
          {
            "fieldPath": "lastUpdatedAtMillis",
            "columnName": "lastUpdatedAtMillis",
            "affinity": "INTEGER"
          },
          {
            "fieldPath": "cashTranchesJson",
            "columnName": "cashTranchesJson",
            "affinity": "TEXT"
          },
          {
            "fieldPath": "addOnsJson",
            "columnName": "addOnsJson",
            "affinity": "TEXT"
          },
          {
            "fieldPath": "syncStatus",
            "columnName": "syncStatus",
            "affinity": "TEXT",
            "notNull": true
          }
        ],
        "primaryKey": {
          "autoGenerate": false,
          "columnNames": [
            "id"
          ]
        },
        "indices": [
          {
            "name": "index_expenses_groupId",
            "unique": false,
            "columnNames": [
              "groupId"
            ],
            "orders": [],
            "createSql": "CREATE INDEX IF NOT EXISTS `index_expenses_groupId` ON `${TABLE_NAME}` (`groupId`)"
          },
          {
            "name": "index_expenses_groupId_syncStatus",
            "unique": false,
            "columnNames": [
              "groupId",
              "syncStatus"
            ],
            "orders": [],
            "createSql": "CREATE INDEX IF NOT EXISTS `index_expenses_groupId_syncStatus` ON `${TABLE_NAME}` (`groupId`, `syncStatus`)"
          }
        ],
        "foreignKeys": [
          {
            "table": "groups",
            "onDelete": "CASCADE",
            "onUpdate": "NO ACTION",
            "columns": [
              "groupId"
            ],
            "referencedColumns": [
              "id"
            ]
          }
        ]
      },
      {
        "tableName": "expense_splits",
        "createSql": "CREATE TABLE IF NOT EXISTS `${TABLE_NAME}` (`id` INTEGER PRIMARY KEY AUTOINCREMENT NOT NULL, `expenseId` TEXT NOT NULL, `userId` TEXT NOT NULL, `amountCents` INTEGER NOT NULL, `percentage` TEXT, `isExcluded` INTEGER NOT NULL, `isCoveredById` TEXT, `subunitId` TEXT, `splitType` TEXT, FOREIGN KEY(`expenseId`) REFERENCES `expenses`(`id`) ON UPDATE NO ACTION ON DELETE CASCADE )",
        "fields": [
          {
            "fieldPath": "id",
            "columnName": "id",
            "affinity": "INTEGER",
            "notNull": true
          },
          {
            "fieldPath": "expenseId",
            "columnName": "expenseId",
            "affinity": "TEXT",
            "notNull": true
          },
          {
            "fieldPath": "userId",
            "columnName": "userId",
            "affinity": "TEXT",
            "notNull": true
          },
          {
            "fieldPath": "amountCents",
            "columnName": "amountCents",
            "affinity": "INTEGER",
            "notNull": true
          },
          {
            "fieldPath": "percentage",
            "columnName": "percentage",
            "affinity": "TEXT"
          },
          {
            "fieldPath": "isExcluded",
            "columnName": "isExcluded",
            "affinity": "INTEGER",
            "notNull": true
          },
          {
            "fieldPath": "isCoveredById",
            "columnName": "isCoveredById",
            "affinity": "TEXT"
          },
          {
            "fieldPath": "subunitId",
            "columnName": "subunitId",
            "affinity": "TEXT"
          },
          {
            "fieldPath": "splitType",
            "columnName": "splitType",
            "affinity": "TEXT"
          }
        ],
        "primaryKey": {
          "autoGenerate": true,
          "columnNames": [
            "id"
          ]
        },
        "indices": [
          {
            "name": "index_expense_splits_expenseId",
            "unique": false,
            "columnNames": [
              "expenseId"
            ],
            "orders": [],
            "createSql": "CREATE INDEX IF NOT EXISTS `index_expense_splits_expenseId` ON `${TABLE_NAME}` (`expenseId`)"
          }
        ],
        "foreignKeys": [
          {
            "table": "expenses",
            "onDelete": "CASCADE",
            "onUpdate": "NO ACTION",
            "columns": [
              "expenseId"
            ],
            "referencedColumns": [
              "id"
            ]
          }
        ]
      },
      {
        "tableName": "contributions",
        "createSql": "CREATE TABLE IF NOT EXISTS `${TABLE_NAME}` (`id` TEXT NOT NULL, `groupId` TEXT NOT NULL, `userId` TEXT NOT NULL, `createdBy` TEXT NOT NULL, `contributionScope` TEXT NOT NULL, `subunitId` TEXT, `linkedExpenseId` TEXT, `amount` INTEGER NOT NULL, `currency` TEXT NOT NULL, `createdAtMillis` INTEGER, `lastUpdatedAtMillis` INTEGER, `syncStatus` TEXT NOT NULL, PRIMARY KEY(`id`), FOREIGN KEY(`groupId`) REFERENCES `groups`(`id`) ON UPDATE NO ACTION ON DELETE CASCADE )",
        "fields": [
          {
            "fieldPath": "id",
            "columnName": "id",
            "affinity": "TEXT",
            "notNull": true
          },
          {
            "fieldPath": "groupId",
            "columnName": "groupId",
            "affinity": "TEXT",
            "notNull": true
          },
          {
            "fieldPath": "userId",
            "columnName": "userId",
            "affinity": "TEXT",
            "notNull": true
          },
          {
            "fieldPath": "createdBy",
            "columnName": "createdBy",
            "affinity": "TEXT",
            "notNull": true
          },
          {
            "fieldPath": "contributionScope",
            "columnName": "contributionScope",
            "affinity": "TEXT",
            "notNull": true
          },
          {
            "fieldPath": "subunitId",
            "columnName": "subunitId",
            "affinity": "TEXT"
          },
          {
            "fieldPath": "linkedExpenseId",
            "columnName": "linkedExpenseId",
            "affinity": "TEXT"
          },
          {
            "fieldPath": "amount",
            "columnName": "amount",
            "affinity": "INTEGER",
            "notNull": true
          },
          {
            "fieldPath": "currency",
            "columnName": "currency",
            "affinity": "TEXT",
            "notNull": true
          },
          {
            "fieldPath": "createdAtMillis",
            "columnName": "createdAtMillis",
            "affinity": "INTEGER"
          },
          {
            "fieldPath": "lastUpdatedAtMillis",
            "columnName": "lastUpdatedAtMillis",
            "affinity": "INTEGER"
          },
          {
            "fieldPath": "syncStatus",
            "columnName": "syncStatus",
            "affinity": "TEXT",
            "notNull": true
          }
        ],
        "primaryKey": {
          "autoGenerate": false,
          "columnNames": [
            "id"
          ]
        },
        "indices": [
          {
            "name": "index_contributions_groupId",
            "unique": false,
            "columnNames": [
              "groupId"
            ],
            "orders": [],
            "createSql": "CREATE INDEX IF NOT EXISTS `index_contributions_groupId` ON `${TABLE_NAME}` (`groupId`)"
          },
          {
            "name": "index_contributions_groupId_linkedExpenseId",
            "unique": false,
            "columnNames": [
              "groupId",
              "linkedExpenseId"
            ],
            "orders": [],
            "createSql": "CREATE INDEX IF NOT EXISTS `index_contributions_groupId_linkedExpenseId` ON `${TABLE_NAME}` (`groupId`, `linkedExpenseId`)"
          },
          {
            "name": "index_contributions_groupId_syncStatus",
            "unique": false,
            "columnNames": [
              "groupId",
              "syncStatus"
            ],
            "orders": [],
            "createSql": "CREATE INDEX IF NOT EXISTS `index_contributions_groupId_syncStatus` ON `${TABLE_NAME}` (`groupId`, `syncStatus`)"
          }
        ],
        "foreignKeys": [
          {
            "table": "groups",
            "onDelete": "CASCADE",
            "onUpdate": "NO ACTION",
            "columns": [
              "groupId"
            ],
            "referencedColumns": [
              "id"
            ]
          }
        ]
      },
      {
        "tableName": "cash_withdrawals",
        "createSql": "CREATE TABLE IF NOT EXISTS `${TABLE_NAME}` (`id` TEXT NOT NULL, `groupId` TEXT NOT NULL, `withdrawnBy` TEXT NOT NULL, `createdBy` TEXT NOT NULL, `withdrawalScope` TEXT NOT NULL, `subunitId` TEXT, `amountWithdrawn` INTEGER NOT NULL, `remainingAmount` INTEGER NOT NULL, `currency` TEXT NOT NULL, `deductedBaseAmount` INTEGER NOT NULL, `exchangeRate` TEXT NOT NULL, `createdAtMillis` INTEGER, `lastUpdatedAtMillis` INTEGER, `addOnsJson` TEXT, `title` TEXT, `notes` TEXT, `receiptLocalUri` TEXT, `syncStatus` TEXT NOT NULL, PRIMARY KEY(`id`), FOREIGN KEY(`groupId`) REFERENCES `groups`(`id`) ON UPDATE NO ACTION ON DELETE CASCADE )",
        "fields": [
          {
            "fieldPath": "id",
            "columnName": "id",
            "affinity": "TEXT",
            "notNull": true
          },
          {
            "fieldPath": "groupId",
            "columnName": "groupId",
            "affinity": "TEXT",
            "notNull": true
          },
          {
            "fieldPath": "withdrawnBy",
            "columnName": "withdrawnBy",
            "affinity": "TEXT",
            "notNull": true
          },
          {
            "fieldPath": "createdBy",
            "columnName": "createdBy",
            "affinity": "TEXT",
            "notNull": true
          },
          {
            "fieldPath": "withdrawalScope",
            "columnName": "withdrawalScope",
            "affinity": "TEXT",
            "notNull": true
          },
          {
            "fieldPath": "subunitId",
            "columnName": "subunitId",
            "affinity": "TEXT"
          },
          {
            "fieldPath": "amountWithdrawn",
            "columnName": "amountWithdrawn",
            "affinity": "INTEGER",
            "notNull": true
          },
          {
            "fieldPath": "remainingAmount",
            "columnName": "remainingAmount",
            "affinity": "INTEGER",
            "notNull": true
          },
          {
            "fieldPath": "currency",
            "columnName": "currency",
            "affinity": "TEXT",
            "notNull": true
          },
          {
            "fieldPath": "deductedBaseAmount",
            "columnName": "deductedBaseAmount",
            "affinity": "INTEGER",
            "notNull": true
          },
          {
            "fieldPath": "exchangeRate",
            "columnName": "exchangeRate",
            "affinity": "TEXT",
            "notNull": true
          },
          {
            "fieldPath": "createdAtMillis",
            "columnName": "createdAtMillis",
            "affinity": "INTEGER"
          },
          {
            "fieldPath": "lastUpdatedAtMillis",
            "columnName": "lastUpdatedAtMillis",
            "affinity": "INTEGER"
          },
          {
            "fieldPath": "addOnsJson",
            "columnName": "addOnsJson",
            "affinity": "TEXT"
          },
          {
            "fieldPath": "title",
            "columnName": "title",
            "affinity": "TEXT"
          },
          {
            "fieldPath": "notes",
            "columnName": "notes",
            "affinity": "TEXT"
          },
          {
            "fieldPath": "receiptLocalUri",
            "columnName": "receiptLocalUri",
            "affinity": "TEXT"
          },
          {
            "fieldPath": "syncStatus",
            "columnName": "syncStatus",
            "affinity": "TEXT",
            "notNull": true
          }
        ],
        "primaryKey": {
          "autoGenerate": false,
          "columnNames": [
            "id"
          ]
        },
        "indices": [
          {
            "name": "index_cash_withdrawals_groupId",
            "unique": false,
            "columnNames": [
              "groupId"
            ],
            "orders": [],
            "createSql": "CREATE INDEX IF NOT EXISTS `index_cash_withdrawals_groupId` ON `${TABLE_NAME}` (`groupId`)"
          },
          {
            "name": "index_cash_withdrawals_groupId_syncStatus",
            "unique": false,
            "columnNames": [
              "groupId",
              "syncStatus"
            ],
            "orders": [],
            "createSql": "CREATE INDEX IF NOT EXISTS `index_cash_withdrawals_groupId_syncStatus` ON `${TABLE_NAME}` (`groupId`, `syncStatus`)"
          },
          {
            "name": "index_cash_withdrawals_groupId_currency_withdrawalScope_remainingAmount",
            "unique": false,
            "columnNames": [
              "groupId",
              "currency",
              "withdrawalScope",
              "remainingAmount"
            ],
            "orders": [],
            "createSql": "CREATE INDEX IF NOT EXISTS `index_cash_withdrawals_groupId_currency_withdrawalScope_remainingAmount` ON `${TABLE_NAME}` (`groupId`, `currency`, `withdrawalScope`, `remainingAmount`)"
          },
          {
            "name": "index_cash_withdrawals_groupId_currency_withdrawalScope_withdrawnBy_remainingAmount",
            "unique": false,
            "columnNames": [
              "groupId",
              "currency",
              "withdrawalScope",
              "withdrawnBy",
              "remainingAmount"
            ],
            "orders": [],
            "createSql": "CREATE INDEX IF NOT EXISTS `index_cash_withdrawals_groupId_currency_withdrawalScope_withdrawnBy_remainingAmount` ON `${TABLE_NAME}` (`groupId`, `currency`, `withdrawalScope`, `withdrawnBy`, `remainingAmount`)"
          },
          {
            "name": "index_cash_withdrawals_groupId_currency_withdrawalScope_subunitId_remainingAmount",
            "unique": false,
            "columnNames": [
              "groupId",
              "currency",
              "withdrawalScope",
              "subunitId",
              "remainingAmount"
            ],
            "orders": [],
            "createSql": "CREATE INDEX IF NOT EXISTS `index_cash_withdrawals_groupId_currency_withdrawalScope_subunitId_remainingAmount` ON `${TABLE_NAME}` (`groupId`, `currency`, `withdrawalScope`, `subunitId`, `remainingAmount`)"
          }
        ],
        "foreignKeys": [
          {
            "table": "groups",
            "onDelete": "CASCADE",
            "onUpdate": "NO ACTION",
            "columns": [
              "groupId"
            ],
            "referencedColumns": [
              "id"
            ]
          }
        ]
      },
      {
        "tableName": "users",
        "createSql": "CREATE TABLE IF NOT EXISTS `${TABLE_NAME}` (`userId` TEXT NOT NULL, `email` TEXT NOT NULL, `displayName` TEXT, `profileImagePath` TEXT, `createdAtMillis` INTEGER, `lastUpdatedAtMillis` INTEGER, `bio` TEXT, `syncStatus` TEXT NOT NULL, PRIMARY KEY(`userId`))",
        "fields": [
          {
            "fieldPath": "userId",
            "columnName": "userId",
            "affinity": "TEXT",
            "notNull": true
          },
          {
            "fieldPath": "email",
            "columnName": "email",
            "affinity": "TEXT",
            "notNull": true
          },
          {
            "fieldPath": "displayName",
            "columnName": "displayName",
            "affinity": "TEXT"
          },
          {
            "fieldPath": "profileImagePath",
            "columnName": "profileImagePath",
            "affinity": "TEXT"
          },
          {
            "fieldPath": "createdAtMillis",
            "columnName": "createdAtMillis",
            "affinity": "INTEGER"
          },
          {
            "fieldPath": "lastUpdatedAtMillis",
            "columnName": "lastUpdatedAtMillis",
            "affinity": "INTEGER"
          },
          {
            "fieldPath": "bio",
            "columnName": "bio",
            "affinity": "TEXT"
          },
          {
            "fieldPath": "syncStatus",
            "columnName": "syncStatus",
            "affinity": "TEXT",
            "notNull": true
          }
        ],
        "primaryKey": {
          "autoGenerate": false,
          "columnNames": [
            "userId"
          ]
        }
      },
      {
        "tableName": "subunits",
        "createSql": "CREATE TABLE IF NOT EXISTS `${TABLE_NAME}` (`id` TEXT NOT NULL, `groupId` TEXT NOT NULL, `name` TEXT NOT NULL, `memberIds` TEXT NOT NULL, `memberShares` TEXT NOT NULL, `createdBy` TEXT NOT NULL, `createdAtMillis` INTEGER, `lastUpdatedAtMillis` INTEGER, `syncStatus` TEXT NOT NULL, PRIMARY KEY(`id`), FOREIGN KEY(`groupId`) REFERENCES `groups`(`id`) ON UPDATE NO ACTION ON DELETE CASCADE )",
        "fields": [
          {
            "fieldPath": "id",
            "columnName": "id",
            "affinity": "TEXT",
            "notNull": true
          },
          {
            "fieldPath": "groupId",
            "columnName": "groupId",
            "affinity": "TEXT",
            "notNull": true
          },
          {
            "fieldPath": "name",
            "columnName": "name",
            "affinity": "TEXT",
            "notNull": true
          },
          {
            "fieldPath": "memberIds",
            "columnName": "memberIds",
            "affinity": "TEXT",
            "notNull": true
          },
          {
            "fieldPath": "memberShares",
            "columnName": "memberShares",
            "affinity": "TEXT",
            "notNull": true
          },
          {
            "fieldPath": "createdBy",
            "columnName": "createdBy",
            "affinity": "TEXT",
            "notNull": true
          },
          {
            "fieldPath": "createdAtMillis",
            "columnName": "createdAtMillis",
            "affinity": "INTEGER"
          },
          {
            "fieldPath": "lastUpdatedAtMillis",
            "columnName": "lastUpdatedAtMillis",
            "affinity": "INTEGER"
          },
          {
            "fieldPath": "syncStatus",
            "columnName": "syncStatus",
            "affinity": "TEXT",
            "notNull": true
          }
        ],
        "primaryKey": {
          "autoGenerate": false,
          "columnNames": [
            "id"
          ]
        },
        "indices": [
          {
            "name": "index_subunits_groupId",
            "unique": false,
            "columnNames": [
              "groupId"
            ],
            "orders": [],
            "createSql": "CREATE INDEX IF NOT EXISTS `index_subunits_groupId` ON `${TABLE_NAME}` (`groupId`)"
          }
        ],
        "foreignKeys": [
          {
            "table": "groups",
            "onDelete": "CASCADE",
            "onUpdate": "NO ACTION",
            "columns": [
              "groupId"
            ],
            "referencedColumns": [
              "id"
            ]
          }
        ]
      }
    ],
    "setupQueries": [
      "CREATE TABLE IF NOT EXISTS room_master_table (id INTEGER PRIMARY KEY,identity_hash TEXT)",
      "INSERT OR REPLACE INTO room_master_table (id,identity_hash) VALUES(42, 'a11a38e1433a563cd60a2a153e91acfd')"
    ]
  }
}